pytest_ipynb/__init__.py
pytest_ipynb/plugin.py
pytest_ipynb-1.1.0.dist-info/DESCRIPTION.rst
pytest_ipynb-1.1.0.dist-info/METADATA
pytest_ipynb-1.1.0.dist-info/RECORD
pytest_ipynb-1.1.0.dist-info/WHEEL
pytest_ipynb-1.1.0.dist-info/entry_points.txt
pytest_ipynb-1.1.0.dist-info/metadata.json
pytest_ipynb-1.1.0.dist-info/top_level.txt
