Metadata-Version: 2.0
Name: pytest-ipynb
Version: 1.1.0
Summary: Use pytest's runner to discover and execute tests as cells of IPython notebooks
Home-page: http://github.com/zonca/pytest-ipynb
Author: Andrea Zonca
Author-email: code@andreazonca.com
License: MIT
Keywords: pytest test unittest ipython notebook
Platform: UNKNOWN
Classifier: Development Status :: 3 - Alpha
Classifier: Intended Audience :: Developers
Classifier: License :: OSI Approved :: MIT License
Classifier: Operating System :: OS Independent
Classifier: Programming Language :: Python :: 2
Classifier: Programming Language :: Python :: 2.7
Classifier: Programming Language :: Python :: 3
Classifier: Programming Language :: Python :: 3.4
Classifier: Programming Language :: C++
Classifier: Topic :: Software Development :: Quality Assurance
Classifier: Topic :: Software Development :: Testing
Requires-Dist: pytest
Requires-Dist: runipy
